app/__init__.py
app/__main__.py
app/config.py
app/server.py
app/tracing.py
app/prompts/__init__.py
app/tools/__init__.py
app/tools/cache.py
app/tools/context.py
app/tools/demo.py
app/tools/health.py
app/tools/secrets.py
app/tools/youtube/__init__.py
app/tools/youtube/client.py
app/tools/youtube/comments.py
app/tools/youtube/live.py
app/tools/youtube/metadata.py
app/tools/youtube/models.py
app/tools/youtube/search.py
app/tools/youtube/transcripts.py
app/tools/youtube/semantic/__init__.py
app/tools/youtube/semantic/chunker.py
app/tools/youtube/semantic/comment_chunker.py
app/tools/youtube/semantic/config.py
app/tools/youtube/semantic/embeddings.py
app/tools/youtube/semantic/indexer.py
app/tools/youtube/semantic/store.py
app/tools/youtube/semantic/tokenizers.py
app/tools/youtube/semantic/tools.py
yt_api_mcp-0.0.3.dist-info/METADATA
yt_api_mcp-0.0.3.dist-info/WHEEL
yt_api_mcp-0.0.3.dist-info/entry_points.txt
yt_api_mcp-0.0.3.dist-info/licenses/LICENSE
yt_api_mcp-0.0.3.dist-info/RECORD
