Metadata-Version: 2.4
Name: yt-api-mcp
Version: 0.0.3
Summary: FastMCP server template with mcp-refcache and Langfuse tracing
Author-email: l4b4r4b4b4 <lucas.cansino@mail.de>
License-File: LICENSE
Requires-Python: >=3.12
Requires-Dist: fastmcp>=2.14.0
Requires-Dist: google-api-python-client>=2.187.0
Requires-Dist: langchain-chroma>=1.1.0
Requires-Dist: langchain-core>=1.2.7
Requires-Dist: langchain-nomic>=1.0.1
Requires-Dist: langchain-text-splitters>=1.1.0
Requires-Dist: langfuse>=3.10.0
Requires-Dist: mcp-refcache>=0.1.0
Requires-Dist: nomic[local]>=3.9.0
Requires-Dist: pydantic-settings>=2.10.0
Requires-Dist: pydantic>=2.10.0
Requires-Dist: tiktoken>=0.12.0
Requires-Dist: typer>=0.15.0
Requires-Dist: youtube-transcript-api>=1.2.3
Provides-Extra: huggingface
Requires-Dist: huggingface-hub>=0.30.0; extra == 'huggingface'
Requires-Dist: tokenizers>=0.21.0; extra == 'huggingface'
